iMSminer/ImzMLParser_chunk.py
iMSminer/__init__.py
iMSminer/data_analysis.py
iMSminer/data_preprocessing.py
iMSminer/utils.py
iMSminer/__pycache__/ImzMLParser_chunk.cpython-310.pyc
iMSminer/__pycache__/ImzMLParser_chunk.cpython-311.pyc
iMSminer/__pycache__/__init__.cpython-310.pyc
iMSminer/__pycache__/__init__.cpython-311.pyc
iMSminer/__pycache__/data_analysis.cpython-310.pyc
iMSminer/__pycache__/data_analysis.cpython-311.pyc
iMSminer/__pycache__/data_preprocessing.cpython-310.pyc
iMSminer/__pycache__/data_preprocessing.cpython-311.pyc
iMSminer/__pycache__/utils.cpython-310.pyc
iMSminer/__pycache__/utils.cpython-311.pyc
iMSminer-1.1.1.dist-info/LICENSE.txt
iMSminer-1.1.1.dist-info/METADATA
iMSminer-1.1.1.dist-info/WHEEL
iMSminer-1.1.1.dist-info/top_level.txt
iMSminer-1.1.1.dist-info/RECORD
