Metadata-Version: 2.1
Name: iMSminer
Version: 1.1.1
Summary: iMSminer provides user-friendly, partially GPU- or compiler-accelerated multi-condition, multi-ROI, and multi-dataset preprocessing and mining of larger-than-memory imaging mass spectrometry datasets in Python.
Home-page: https://github.com/Prentice-lab-UF/iMSminer
Author: Yu Tin Lin
Author-email: yutinlin@stanford.edu
License: Apache Software License
Classifier: Development Status :: 3 - Alpha
Classifier: Intended Audience :: Developers
Classifier: Programming Language :: Python :: 3
Requires-Python: >=3.6
License-File: LICENSE.txt
Requires-Dist: bokeh==3.4.1
Requires-Dist: opencv-python==4.10.0.84
Requires-Dist: matplotlib==3.7.1
Requires-Dist: msalign==0.2.0
Requires-Dist: networkx==3.2.1
Requires-Dist: numba==0.60.0
Requires-Dist: numpy==1.26.0
Requires-Dist: pandas==1.5.3
Requires-Dist: psutil==5.9.0
Requires-Dist: pyimzml==1.5.4
Requires-Dist: scikit-learn==1.6.0
Requires-Dist: scipy==1.14.1
Requires-Dist: seaborn==0.11.2
Requires-Dist: statsmodels==0.14.2
